flashlearn/__init__.py
flashlearn/core/__init__.py
flashlearn/core/flash_client.py
flashlearn/core/orchestration.py
flashlearn/core/tests/test_flash_client.py
flashlearn/core/tests/test_orchestration.py
flashlearn/skills/__init__.py
flashlearn/skills/base_data_skill.py
flashlearn/skills/base_skill.py
flashlearn/skills/classification.py
flashlearn/skills/collect_all_code.py
flashlearn/skills/discover_labels.py
flashlearn/skills/general_skill.py
flashlearn/skills/learn_skill.py
flashlearn/skills/tests/test_base_data_skill.py
flashlearn/skills/tests/test_base_skill.py
flashlearn/skills/tests/test_classification.py
flashlearn/skills/tests/test_discover_labels.py
flashlearn/skills/tests/test_general_skill.py
flashlearn/skills/tests/test_learn_skill.py
flashlearn/skills/toolkit/__init__.py
flashlearn/skills/toolkit/generate_init.py
flashlearn/skills/toolkit/generate_toolkit.py
flashlearn/skills/toolkit/simple_search.py
flashlearn/skills/toolkit/validate_json_files.py
flashlearn/utils/__init__.py
flashlearn/utils/demo_data.py
flashlearn/utils/logging_utils.py
flashlearn/utils/token_utils.py
flashlearn/utils/tests/test_demo_data.py
flashlearn/utils/tests/test_token_utils.py
flashlearn-1.0.4.dist-info/LICENSE.md
flashlearn-1.0.4.dist-info/METADATA
flashlearn-1.0.4.dist-info/WHEEL
flashlearn-1.0.4.dist-info/top_level.txt
flashlearn-1.0.4.dist-info/RECORD
